{"Name":"Manhu","Level":1,"Experience":0,"SkillPoints":0,"Strength":10,"Dexterity":10,"Constitution":10,"Intelligence":10,"Wisdom":10,"Charisma":10,"BaseHealth":8,"Health":18,"Speed":40,"Sanity":100,"Skills":{"Range":{"Name":"Range","Level":1,"Experience":0},"Melee":{"Name":"Melee","Level":1,"Experience":0},"Medicine":{"Name":"Medicine","Level":1,"Experience":0},"Speaking":{"Name":"Speaking","Level":1,"Experience":0},"Cooking":{"Name":"Cooking","Level":1,"Experience":0},"Alchemy":{"Name":"Alchemy","Level":1,"Experience":0},"Survival":{"Name":"Survival","Level":1,"Experience":0},"Crafting":{"Name":"Crafting","Level":1,"Experience":0},"Lore":{"Name":"Lore","Level":1,"Experience":0},"Sailing":{"Name":"Sailing","Level":1,"Experience":0},"Stealth":{"Name":"Stealth","Level":1,"Experience":0},"Hunting":{"Name":"Hunting","Level":1,"Experience":0},"Tinkering":{"Name":"Tinkering","Level":1,"Experience":0},"Diplomacy":{"Name":"Diplomacy","Level":1,"Experience":0},"Channeling":{"Name":"Channeling","Level":1,"Experience":0}},"CanChannel":true,"ChannelingPower":"Kaido","Inventory":[],"EquipmentSlots":{"Helmet/Hat":null,"Face":null,"Neck":null,"Chest":null,"Hands":null,"Waist":null,"Left Arm":null,"Right Arm":null,"Left Leg":null,"Right Leg":null,"Feet":null},"CurrentRegion":"The Sun Spur","CurrentLocation":"Port Waveward"}